protatoquests/__init__.py
protatoquests/proxy.py
protatoquests-1.0.2.dist-info/LICENSE
protatoquests-1.0.2.dist-info/METADATA
protatoquests-1.0.2.dist-info/WHEEL
protatoquests-1.0.2.dist-info/RECORD
