Metadata-Version: 2.1
Name: protatoquests
Version: 1.0.2
Summary: Automatic proxy rotation for anonymous web requests.
Home-page: https://github.com/nicoloboschi/protatoquests
License: MIT
Keywords: scraping,webscraping,proxy,socks5,requests,http
Author: Nicolò Boschi
Author-email: boschi1997@gmail.com
Requires-Python: >=3.9,<4.0
Classifier: License :: OSI Approved :: MIT License
Classifier: Programming Language :: Python :: 3
Classifier: Programming Language :: Python :: 3.9
Classifier: Programming Language :: Python :: 3.10
Classifier: Programming Language :: Python :: 3.11
Classifier: Programming Language :: Python :: 3.12
Requires-Dist: beautifulsoup4 (>=4,<5)
Requires-Dist: requests[socks] (>=2.32.3,<3.0.0)
Project-URL: Documentation, https://github.com/nicoloboschi/protatoquests
Project-URL: Repository, https://github.com/nicoloboschi/protatoquests
